README.txt
setup.py
commentator/__init__.py
commentator/example.py
commentator/handlers.py
commentator/middleware.py
commentator/model.py
commentator.egg-info/PKG-INFO
commentator.egg-info/SOURCES.txt
commentator.egg-info/dependency_links.txt
commentator.egg-info/entry_points.txt
commentator.egg-info/not-zip-safe
commentator.egg-info/requires.txt
commentator.egg-info/top_level.txt