Metadata-Version: 1.0
Name: commentator
Version: 0.1
Summary: WSGI commenting middleware
Home-page: http://k0s.org/hg/commentator
Author: Jeff Hammel
Author-email: k0scist@gmail.com
License: GPL
Platform: UNKNOWN
